[
  {
    "name": "landslides-thresholds",
    "organization": "U.S. Geological Survey",
    "description": "Software for tracking rainfall thresholds for landslide and debris-flow occurrence (A collection of Fortran programs, Python scripts, shell scripts and Windows batch files along with sample data)",
    "version": "1.0.0",
    "status": "Production",

    "permissions": {
      "usageType": "openSource",
      "licenses": [
        {
          "name": "Public Domain, CC0-1.0",
          "URL": "https://my.usgs.gov/bitbucket/users/baum_usgs.gov/repos/landslides-thresholds/browse/LICENSE.md"
        }
      ]
    },

    "homepageURL": "https://my.usgs.gov/bitbucket/users/baum_usgs.gov/repos/landslides-thresholds/browse",
    "downloadURL": "https://my.usgs.gov/bitbucket/rest/api/latest/projects/~BAUM_USGS.GOV/repos/landslides-thresholds/archive?format=zip",
    "disclaimerURL": "https://my.usgs.gov/bitbucket/users/baum_usgs.gov/repos/landslides-thresholds/browse/DISCLAIMER.md",
    "repositoryUrl": "https://my.usgs.gov/bitbucket/scm/~baum_usgs.gov/landslides-thresholds.git",
    "vcs": "git",

    "laborHours": null,

    "tags": [
      "Natural Hazards",
      "Geologic Hazards Science Center",
      "Precipitation thresholds"
      "Landslides"
    ],

    "languages": [
      "Fortran 90",
      "Python 2.7"
    ],

    "contact": {
      "name": "Rex Baum",
      "email": "baum@usgs.gov"
    },

    "date": {
      "metadataLastUpdated": "2018-03-02"
    }
  }
]
